<PAMDataset>
  <PAMRasterBand band="1">
    <Histograms>
      <HistItem>
        <HistMin>0.0001335344713879749</HistMin>
        <HistMax>1</HistMax>
        <BucketCount>256</BucketCount>
        <IncludeOutOfRange>1</IncludeOutOfRange>
        <Approximate>0</Approximate>
        <HistCounts>56|37|36|30|38|26|27|23|19|27|32|20|33|19|35|20|18|25|16|20|33|18|23|22|31|23|12|26|14|22|19|18|21|27|24|21|20|20|13|30|22|21|19|25|29|27|32|18|18|18|24|27|22|21|26|25|21|13|23|17|24|25|32|32|17|25|19|26|16|30|26|34|18|36|14|24|19|20|21|20|21|21|25|28|30|29|30|24|29|33|22|27|24|27|30|27|21|26|17|23|22|26|29|21|29|22|26|18|28|20|21|24|29|20|34|27|21|12|18|24|26|22|23|24|30|22|30|28|47|53|64|47|56|55|43|43|36|54|45|51|47|55|38|61|53|44|45|51|43|54|64|52|52|60|66|36|51|57|39|58|54|40|52|41|58|45|45|48|51|36|47|44|54|54|54|47|59|42|59|50|59|69|62|53|60|67|68|45|58|48|42|56|54|62|53|52|52|63|55|56|48|68|61|63|50|64|68|67|64|68|90|68|57|68|65|94|66|64|79|82|60|82|70|62|60|73|68|72|79|84|73|87|86|89|99|89|102|86|97|98|107|100|118|107|98|96|108|110|98|107|100|113|106|104|110|119124</HistCounts>
      </HistItem>
    </Histograms>
    <Metadata>
      <MDI key="RepresentationType">ATHEMATIC</MDI>
      <MDI key="STATISTICS_EXCLUDEDVALUES"></MDI>
      <MDI key="STATISTICS_MAXIMUM">1</MDI>
      <MDI key="STATISTICS_MEAN">0.96840870740033</MDI>
      <MDI key="STATISTICS_MINIMUM">0.00013353447138797</MDI>
      <MDI key="STATISTICS_SKIPFACTORX">1</MDI>
      <MDI key="STATISTICS_SKIPFACTORY">1</MDI>
      <MDI key="STATISTICS_STDDEV">0.13162938678678</MDI>
    </Metadata>
  </PAMRasterBand>
</PAMDataset>
