<PAMDataset>
  <PAMRasterBand band="1">
    <Histograms>
      <HistItem>
        <HistMin>2.926867819041945e-05</HistMin>
        <HistMax>1</HistMax>
        <BucketCount>256</BucketCount>
        <IncludeOutOfRange>1</IncludeOutOfRange>
        <Approximate>0</Approximate>
        <HistCounts>39|40|37|33|41|28|33|18|35|23|21|27|18|25|30|27|21|20|26|26|21|23|32|22|31|19|22|23|19|19|18|30|14|20|28|29|29|16|28|19|30|17|30|24|17|28|27|26|26|31|25|29|24|21|33|25|27|28|18|16|22|26|23|25|24|20|25|19|19|21|27|22|17|17|27|18|30|29|20|23|35|29|23|33|24|31|24|22|20|28|29|17|26|37|23|22|21|43|35|26|35|35|34|32|23|32|29|24|18|33|33|48|39|33|28|37|30|40|28|39|33|36|33|33|46|39|31|25|33|29|38|28|41|41|39|37|30|27|35|30|38|37|40|36|33|41|26|38|25|29|43|53|36|37|38|37|40|36|39|37|45|47|37|59|49|50|39|47|69|48|52|53|54|58|53|69|56|54|51|48|60|58|58|56|52|43|60|49|58|51|46|48|60|54|58|49|44|48|48|72|52|51|54|51|58|56|47|60|57|67|48|53|56|47|48|40|72|57|47|42|39|56|62|55|53|53|56|52|61|60|62|59|62|60|77|43|68|66|62|74|71|55|74|69|75|61|56|57|60|67|66|59|70|56|62|66686</HistCounts>
      </HistItem>
    </Histograms>
    <Metadata>
      <MDI key="RepresentationType">ATHEMATIC</MDI>
      <MDI key="STATISTICS_EXCLUDEDVALUES"></MDI>
      <MDI key="STATISTICS_MAXIMUM">1</MDI>
      <MDI key="STATISTICS_MEAN">0.94748172181111</MDI>
      <MDI key="STATISTICS_MINIMUM">2.9268678190419e-05</MDI>
      <MDI key="STATISTICS_SKIPFACTORX">1</MDI>
      <MDI key="STATISTICS_SKIPFACTORY">1</MDI>
      <MDI key="STATISTICS_STDDEV">0.17006925395944</MDI>
    </Metadata>
  </PAMRasterBand>
</PAMDataset>
