<PAMDataset>
  <PAMRasterBand band="1">
    <Histograms>
      <HistItem>
        <HistMin>2.616202800709289e-05</HistMin>
        <HistMax>1</HistMax>
        <BucketCount>256</BucketCount>
        <IncludeOutOfRange>1</IncludeOutOfRange>
        <Approximate>0</Approximate>
        <HistCounts>62|26|38|34|43|37|37|37|39|40|44|36|39|50|37|32|29|38|44|30|33|30|33|28|29|45|41|33|46|31|38|37|34|39|28|42|43|36|32|25|22|35|35|43|31|36|35|44|31|30|38|29|35|40|32|44|34|46|36|36|25|37|51|35|41|40|40|36|35|52|51|36|48|48|48|36|51|41|42|37|38|53|45|61|57|53|45|49|54|40|54|45|60|44|52|42|45|39|50|44|53|41|51|38|55|43|39|40|39|40|53|50|41|51|37|43|54|44|49|47|39|40|57|53|53|49|53|43|39|36|41|39|39|40|31|37|45|32|34|58|34|31|49|40|42|57|34|37|50|53|50|37|52|41|47|47|52|30|51|48|37|49|46|41|48|48|49|41|43|47|42|54|52|64|54|67|53|65|58|45|48|45|53|43|35|32|41|37|40|48|58|52|43|35|42|40|62|49|52|44|35|43|46|50|46|42|38|41|38|47|43|36|53|44|48|49|52|44|50|43|49|43|51|58|47|50|48|54|41|51|58|49|50|34|52|60|46|52|68|43|44|41|55|45|45|42|46|55|51|41|50|52|41|45|42|6404</HistCounts>
      </HistItem>
    </Histograms>
    <Metadata>
      <MDI key="RepresentationType">ATHEMATIC</MDI>
      <MDI key="STATISTICS_EXCLUDEDVALUES"></MDI>
      <MDI key="STATISTICS_MAXIMUM">1</MDI>
      <MDI key="STATISTICS_MEAN">0.6964244247922</MDI>
      <MDI key="STATISTICS_MINIMUM">2.6162028007093e-05</MDI>
      <MDI key="STATISTICS_SKIPFACTORX">1</MDI>
      <MDI key="STATISTICS_SKIPFACTORY">1</MDI>
      <MDI key="STATISTICS_STDDEV">0.32241506005495</MDI>
    </Metadata>
  </PAMRasterBand>
</PAMDataset>
