<PAMDataset>
  <PAMRasterBand band="1">
    <Histograms>
      <HistItem>
        <HistMin>0.004268919117748737</HistMin>
        <HistMax>1</HistMax>
        <BucketCount>256</BucketCount>
        <IncludeOutOfRange>1</IncludeOutOfRange>
        <Approximate>0</Approximate>
        <HistCounts>198|103|69|75|82|87|72|70|71|69|61|74|68|65|70|78|60|70|69|63|77|90|70|67|74|65|64|64|54|54|42|41|48|37|48|34|53|47|38|45|45|34|33|34|45|33|27|42|43|36|29|40|40|41|37|26|37|30|40|36|37|41|43|38|29|32|31|49|43|31|32|31|38|37|38|38|42|52|34|47|36|34|38|38|37|40|30|37|49|30|39|40|31|40|39|28|30|41|26|38|39|30|49|32|39|43|30|40|39|42|40|40|37|42|36|34|42|40|42|41|43|53|42|54|43|58|49|202|332|314|282|278|289|259|256|244|243|210|254|219|212|233|245|210|223|229|236|234|250|237|290|312|280|287|292|299|279|262|264|268|236|244|252|232|232|263|234|264|261|268|228|232|190|272|236|191|203|208|191|164|187|170|211|171|177|171|157|166|138|141|116|138|145|119|138|144|101|131|121|117|94|86|96|84|102|91|97|78|84|78|90|96|72|88|65|89|75|83|90|84|80|53|93|83|78|79|75|68|67|77|74|76|63|69|71|64|69|71|47|66|83|74|69|58|68|58|59|49|56|57|62|68|54|63|59|2459</HistCounts>
      </HistItem>
    </Histograms>
    <Metadata>
      <MDI key="RepresentationType">ATHEMATIC</MDI>
      <MDI key="STATISTICS_EXCLUDEDVALUES"></MDI>
      <MDI key="STATISTICS_MAXIMUM">1</MDI>
      <MDI key="STATISTICS_MEAN">0.6073906346688</MDI>
      <MDI key="STATISTICS_MINIMUM">0.0042689191177487</MDI>
      <MDI key="STATISTICS_SKIPFACTORX">1</MDI>
      <MDI key="STATISTICS_SKIPFACTORY">1</MDI>
      <MDI key="STATISTICS_STDDEV">0.25477149231905</MDI>
    </Metadata>
  </PAMRasterBand>
</PAMDataset>
