<PAMDataset>
  <PAMRasterBand band="1">
    <Histograms>
      <HistItem>
        <HistMin>5.795724064228125e-05</HistMin>
        <HistMax>0.4241935312747955</HistMax>
        <BucketCount>256</BucketCount>
        <IncludeOutOfRange>1</IncludeOutOfRange>
        <Approximate>0</Approximate>
        <HistCounts>172|245|413|356|315|232|207|218|204|214|240|245|229|226|250|240|286|289|303|314|236|264|249|265|280|287|295|304|308|298|329|291|310|311|310|332|321|333|307|323|329|316|319|319|358|367|356|381|368|369|360|330|335|338|346|366|363|344|360|373|351|333|367|392|372|343|359|383|344|365|399|404|395|388|402|387|390|411|429|430|416|447|411|434|436|466|400|383|405|395|383|399|408|413|394|451|432|457|400|414|399|425|411|437|432|443|482|522|532|575|475|558|559|501|500|514|479|499|491|601|535|493|497|513|517|539|542|502|551|539|444|440|397|380|369|366|356|319|299|292|285|286|299|273|286|226|241|219|228|230|239|269|242|228|256|208|241|200|207|196|221|227|201|182|166|170|141|153|141|166|174|150|145|134|131|113|122|115|127|109|110|101|101|91|104|114|117|102|114|114|88|109|93|77|92|83|78|90|82|103|78|62|72|75|79|64|62|59|50|56|50|45|54|58|43|50|36|47|44|47|29|33|31|30|32|25|28|31|22|32|16|21|17|16|13|9|11|11|9|9|10|3|6|7|6|7|4|2|2|4|5|1|0|1|0|2</HistCounts>
      </HistItem>
    </Histograms>
    <Metadata>
      <MDI key="RepresentationType">ATHEMATIC</MDI>
      <MDI key="STATISTICS_EXCLUDEDVALUES"></MDI>
      <MDI key="STATISTICS_MAXIMUM">0.4241935312748</MDI>
      <MDI key="STATISTICS_MEAN">0.15633347889416</MDI>
      <MDI key="STATISTICS_MINIMUM">5.7957240642281e-05</MDI>
      <MDI key="STATISTICS_SKIPFACTORX">1</MDI>
      <MDI key="STATISTICS_SKIPFACTORY">1</MDI>
      <MDI key="STATISTICS_STDDEV">0.084709955234753</MDI>
    </Metadata>
  </PAMRasterBand>
</PAMDataset>
