<PAMDataset>
  <PAMRasterBand band="1">
    <Histograms>
      <HistItem>
        <HistMin>0.0004576932697091252</HistMin>
        <HistMax>1</HistMax>
        <BucketCount>256</BucketCount>
        <IncludeOutOfRange>1</IncludeOutOfRange>
        <Approximate>0</Approximate>
        <HistCounts>27|14|22|13|20|22|24|14|20|16|17|15|17|10|13|19|21|22|12|18|17|17|22|17|15|20|23|17|15|27|12|17|23|19|19|12|19|21|13|25|20|25|18|18|21|25|21|23|15|19|17|17|21|20|16|23|22|24|32|23|33|23|25|22|28|13|19|21|18|17|26|19|24|25|24|46|29|28|23|25|24|23|34|30|31|24|22|27|23|24|14|28|30|27|34|24|26|25|32|23|28|33|18|24|24|30|24|19|22|25|24|24|29|23|19|24|26|26|25|24|19|21|26|21|22|15|30|20|119|140|118|126|138|149|136|100|119|110|120|120|113|119|114|122|113|108|100|129|102|101|93|103|96|76|77|68|58|80|65|72|66|64|75|58|66|49|56|52|44|47|57|60|56|53|45|47|42|45|52|60|58|67|65|57|74|43|41|33|28|20|24|27|32|24|15|12|12|13|17|8|7|15|7|10|7|10|6|11|8|10|4|10|11|7|9|4|5|8|7|5|3|2|1|2|7|2|1|1|2|2|1|2|4|2|2|4|2|3|1|1|2|0|3|1|0|6|1|1|6|0|1|0|3|2|2|6</HistCounts>
      </HistItem>
    </Histograms>
    <Metadata>
      <MDI key="RepresentationType">ATHEMATIC</MDI>
      <MDI key="STATISTICS_EXCLUDEDVALUES"></MDI>
      <MDI key="STATISTICS_MAXIMUM">1</MDI>
      <MDI key="STATISTICS_MEAN">0.49383657749854</MDI>
      <MDI key="STATISTICS_MINIMUM">0.00045769326970913</MDI>
      <MDI key="STATISTICS_SKIPFACTORX">1</MDI>
      <MDI key="STATISTICS_SKIPFACTORY">1</MDI>
      <MDI key="STATISTICS_STDDEV">0.19693537887338</MDI>
    </Metadata>
  </PAMRasterBand>
</PAMDataset>
